{
  "version": 2,
  "name": "vilnius",
  "alias": "mansurov.me",
  "env": {
    "MAPBOX_TOKEN": "@mapbox_token",
    "GOODREADS_KEY": "@goodreads_key",
    "TUMBLR_CONSUMER_KEY": "@tumblr_consumer_key"
  },
  "build": {
    "env": {
      "MAPBOX_TOKEN": "@mapbox_token",
      "GOODREADS_KEY": "@goodreads_key",
      "TUMBLR_CONSUMER_KEY": "@tumblr_consumer_key"
    }
  },
  "builds": [
    {
      "src": "package.json",
      "use": "@now/static-build",
      "config": {
        "distDir": "public"
      }
    }
  ]
}